MANIFEST.in
setup.py
ansible/module_utils/alicloud_ecs.py
ansible/module_utils/alicloud_oss.py
ansible_alicloud_module_utils.egg-info/PKG-INFO
ansible_alicloud_module_utils.egg-info/SOURCES.txt
ansible_alicloud_module_utils.egg-info/dependency_links.txt
ansible_alicloud_module_utils.egg-info/requires.txt
ansible_alicloud_module_utils.egg-info/top_level.txt